eTouch/ChangeOrder.py
eTouch/Incident.py
eTouch/Workflow.py
eTouch/__init__.py
eTouch/eTouch.py
eTouch-0.0.3.dist-info/METADATA
eTouch-0.0.3.dist-info/WHEEL
eTouch-0.0.3.dist-info/top_level.txt
eTouch-0.0.3.dist-info/RECORD
